zds_client/__init__.py
zds_client/auth.py
zds_client/client.py
zds_client/generate_jwt.py
zds_client/oas.py
zds_client/schema.py
gemma_zds_client-2.0.0.dist-info/METADATA
gemma_zds_client-2.0.0.dist-info/WHEEL
gemma_zds_client-2.0.0.dist-info/entry_points.txt
gemma_zds_client-2.0.0.dist-info/top_level.txt
gemma_zds_client-2.0.0.dist-info/RECORD
